datafact_proj/__about__.py
datafact_proj/__init__.py
datafact_proj-0.0.1.dist-info/METADATA
datafact_proj-0.0.1.dist-info/WHEEL
datafact_proj-0.0.1.dist-info/licenses/LICENSE.txt
datafact_proj-0.0.1.dist-info/RECORD
